{
  "type": "Feature",
  "properties": {
    "gn:gn_country":"AS",
    "gn:gn_fcode":"PPL",
    "gn:gn_pop":1868,
    "gn:population":1868,
    "iso:country":"AS",
    "name:azb_x_preferred":[
        "\u0641\u0642\u0627\u062a\u0648\u0642\u0648"
    ],
    "name:bos_x_preferred":[
        "Fagatogo"
    ],
    "name:ceb_x_preferred":[
        "Fagatogo"
    ],
    "name:ces_x_preferred":[
        "Fagatogo"
    ],
    "name:cym_x_preferred":[
        "Fagatogo"
    ],
    "name:deu_x_preferred":[
        "Fagatogo"
    ],
    "name:eng_x_preferred":[
        "Fagatogo"
    ],
    "name:fas_x_preferred":[
        "\u0641\u06af\u0627\u062a\u0648\u06af\u0648"
    ],
    "name:fra_x_preferred":[
        "Fagatogo"
    ],
    "name:gla_x_preferred":[
        "Fagatogo"
    ],
    "name:heb_x_preferred":[
        "\u05e4\u05d0\u05d2\u05d0\u05d8\u05d5\u05d2\u05d5"
    ],
    "name:ita_x_preferred":[
        "Fagatogo"
    ],
    "name:jpn_x_preferred":[
        "\u30d5\u30a1\u30ac\u30c8\u30b4"
    ],
    "name:mkd_x_preferred":[
        "\u0424\u0430\u0433\u0430\u0442\u043e\u0433\u043e"
    ],
    "name:msa_x_preferred":[
        "Fagatogo"
    ],
    "name:nld_x_preferred":[
        "Fagatogo"
    ],
    "name:pol_x_preferred":[
        "Fagatogo"
    ],
    "name:por_x_preferred":[
        "Fagatogo"
    ],
    "name:rus_x_preferred":[
        "\u0424\u0430\u0433\u0430\u0442\u043e\u0433\u043e"
    ],
    "name:spa_x_preferred":[
        "Fagatogo"
    ],
    "name:srp_x_preferred":[
        "\u0424\u0430\u0433\u0430\u0442\u043e\u0433\u043e"
    ],
    "name:swe_x_preferred":[
        "Fagatogo"
    ],
    "name:unk_x_variant":[
        "Fanga Tonga"
    ],
    "name:urd_x_preferred":[
        "\u0641\u0627\u06af\u0627\u0679\u0648\u06af\u0648"
    ],
    "name:war_x_preferred":[
        "Fagatogo"
    ],
    "name:zho_x_preferred":[
        "\u6cd5\u52a0\u6258\u6208"
    ],
    "qs_pg:aaroncc":"AS",
    "qs_pg:gn_country":"AS",
    "qs_pg:gn_fcode":"PPL",
    "qs_pg:gn_pop":1868,
    "qs_pg:name":"Fagatogo",
    "qs_pg:name_adm0":"American Samoa",
    "qs_pg:name_adm1":"Eastern",
    "qs_pg:photos_9k":1,
    "qs_pg:photos_9r":1,
    "qs_pg:photos_all":4,
    "qs_pg:photos_sr":0,
    "qs_pg:pop_sr":3,
    "qs_pg:qs_pg_placetype":"locality",
    "qs_pg:qs_pg_placetype_gp":"Town",
    "qs_pg:woe_adm0":23424746,
    "woe:adm0_id":23424746,
    "woe:name_adm0":"American Samoa",
    "woe:name_adm1":"Eastern",
    "woe:placetype":"Town",
    "wof:name":"Fagatogo",
    "wof:placetype":"locality",
    "wof:population":1868
},
  "geometry": {"coordinates":[-170.69,-14.2825],"type":"Point"}
}