{
  "type": "Feature",
  "properties": {
    "gn:admin1_code":"010",
    "gn:asciiname":"Ogefao",
    "gn:country_code":"AS",
    "gn:dem":137,
    "gn:elevation":"118.0",
    "gn:feature_class":"P",
    "gn:feature_code":"PPL",
    "gn:name":"Ogefao",
    "gn:population":0,
    "gn:timezone":"Pacific/Pago_Pago",
    "iso:country":"AS",
    "wof:name":"Ogefao",
    "wof:placetype":"locality"
},
  "geometry": {"coordinates":[-170.57778000000005,-14.25389],"type":"Point"}
}