{
  "type": "Feature",
  "properties": {
    "gn:country":"AS",
    "gn:fcode":"PPL",
    "gn:population":2052,
    "iso:country":"AS",
    "qs_pg:aaroncc":"AS",
    "qs_pg:gn_country":"AS",
    "qs_pg:gn_fcode":"PPL",
    "qs_pg:gn_pop":2052,
    "qs_pg:name":"Mapusagafou",
    "qs_pg:photos_9r":0,
    "qs_pg:photos_sr":0,
    "qs_pg:pop_sr":4,
    "qs_pg:qs_pg_placetype":"locality",
    "wof:name":"Mapusagafou",
    "wof:placetype":"locality",
    "wof:population":2052
},
  "geometry": {"coordinates":[-170.75278,-14.33056],"type":"Point"}
}