{
  "type": "Feature",
  "properties": {
    "gn:admin1_code":"050",
    "gn:asciiname":"Tafunafou",
    "gn:country_code":"AS",
    "gn:dem":30,
    "gn:elevation":"23.0",
    "gn:feature_class":"P",
    "gn:feature_code":"PPL",
    "gn:name":"Tafunafou",
    "gn:population":0,
    "gn:timezone":"Pacific/Pago_Pago",
    "iso:country":"AS",
    "wof:name":"Tafunafou",
    "wof:placetype":"locality"
},
  "geometry": {"coordinates":[-170.73083,-14.32917],"type":"Point"}
}