{
  "type": "Feature",
  "properties": {
    "gn:admin1_code":"010",
    "gn:asciiname":"Si'ufaga",
    "gn:country_code":"AS",
    "gn:dem":28,
    "gn:elevation":"17.0",
    "gn:feature_class":"P",
    "gn:feature_code":"PPL",
    "gn:name":"Si\u2018ufaga",
    "gn:population":0,
    "gn:timezone":"Pacific/Pago_Pago",
    "iso:country":"AS",
    "name:und_x_variant":[
        "Siufaga"
    ],
    "wof:name":"Si'ufaga",
    "wof:placetype":"locality"
},
  "geometry": {"coordinates":[-170.69888999999995,-14.275],"type":"Point"}
}