{
  "type": "Feature",
  "properties": {
    "gn:admin1_code":"050",
    "gn:asciiname":"Fagalele",
    "gn:country_code":"AS",
    "gn:dem":23,
    "gn:elevation":"4.0",
    "gn:feature_class":"P",
    "gn:feature_code":"PPL",
    "gn:name":"Fagalele",
    "gn:population":0,
    "gn:timezone":"Pacific/Pago_Pago",
    "iso:country":"AS",
    "wof:name":"Fagalele",
    "wof:placetype":"locality"
},
  "geometry": {"coordinates":[-170.78443999999999,-14.34667],"type":"Point"}
}