{
  "type": "Feature",
  "properties": {
    "gn:admin1_code":"010",
    "gn:asciiname":"Utuloa",
    "gn:country_code":"AS",
    "gn:dem":147,
    "gn:elevation":"118.0",
    "gn:feature_class":"P",
    "gn:feature_code":"PPL",
    "gn:name":"Utuloa",
    "gn:population":0,
    "gn:timezone":"Pacific/Pago_Pago",
    "iso:country":"AS",
    "wof:name":"Utuloa",
    "wof:placetype":"locality"
},
  "geometry": {"coordinates":[-170.61722,-14.26444],"type":"Point"}
}