{
  "type": "Feature",
  "properties": {
    "gn:admin1_code":"050",
    "gn:asciiname":"Tuaolo",
    "gn:country_code":"AS",
    "gn:dem":281,
    "gn:elevation":"282.0",
    "gn:feature_class":"P",
    "gn:feature_code":"PPL",
    "gn:name":"Tuaolo",
    "gn:population":0,
    "gn:timezone":"Pacific/Pago_Pago",
    "iso:country":"AS",
    "name:und_x_variant":[
        "Tu\u00e4`olo"
    ],
    "wof:name":"Tuaolo",
    "wof:placetype":"locality"
},
  "geometry": {"coordinates":[-170.75916999999995,-14.31944],"type":"Point"}
}