{
  "type": "Feature",
  "properties": {
    "gn:admin1_code":"050",
    "gn:asciiname":"Lepine",
    "gn:country_code":"AS",
    "gn:dem":24,
    "gn:elevation":"18.0",
    "gn:feature_class":"P",
    "gn:feature_code":"PPL",
    "gn:name":"Lepine",
    "gn:population":0,
    "gn:timezone":"Pacific/Pago_Pago",
    "iso:country":"AS",
    "name:deu_x_preferred":[
        "L\u00e9pine"
    ],
    "name:fra_x_preferred":[
        "L\u00e9pine"
    ],
    "name:ita_x_preferred":[
        "L\u00e9pine"
    ],
    "wof:name":"Lepine",
    "wof:placetype":"locality"
},
  "geometry": {"coordinates":[-170.72778,-14.32389],"type":"Point"}
}